ADMIN.txt
CHANGELOG.txt
LICENSE.txt
MANIFEST.in
README.rst
httpd.conf.sample
manage-ngpy
ngpy.cfg
ngpy.wsgi
run-ngpy
setup.py
simd
ngpy/__init__.py
ngpy/config.py
ngpy/forms.py
ngpy/ngofflattice_kooi.py
ngpy/ngplot.py
ngpy/ngrc.ini
ngpy/ngrun.py
ngpy/ngutil.py
ngpy/ngzodb.py
ngpy/particle.py
ngpy/vector2d.py
ngpy/views.py
ngpy.egg-info/PKG-INFO
ngpy.egg-info/SOURCES.txt
ngpy.egg-info/dependency_links.txt
ngpy.egg-info/not-zip-safe
ngpy.egg-info/requires.txt
ngpy.egg-info/top_level.txt
ngpy/static/jquery-1.6.4.js
ngpy/static/style.css
ngpy/static/themes/base/jquery-ui.css
ngpy/static/themes/base/jquery.ui.accordion.css
ngpy/static/themes/base/jquery.ui.all.css
ngpy/static/themes/base/jquery.ui.autocomplete.css
ngpy/static/themes/base/jquery.ui.base.css
ngpy/static/themes/base/jquery.ui.button.css
ngpy/static/themes/base/jquery.ui.core.css
ngpy/static/themes/base/jquery.ui.datepicker.css
ngpy/static/themes/base/jquery.ui.dialog.css
ngpy/static/themes/base/jquery.ui.menu.css
ngpy/static/themes/base/jquery.ui.menubar.css
ngpy/static/themes/base/jquery.ui.progressbar.css
ngpy/static/themes/base/jquery.ui.resizable.css
ngpy/static/themes/base/jquery.ui.selectable.css
ngpy/static/themes/base/jquery.ui.slider.css
ngpy/static/themes/base/jquery.ui.spinner.css
ngpy/static/themes/base/jquery.ui.tabs.css
ngpy/static/themes/base/jquery.ui.theme.css
ngpy/static/themes/base/jquery.ui.tooltip.css
ngpy/static/themes/base/images/ui-bg_flat_0_aaaaaa_40x100.png
ngpy/static/themes/base/images/ui-bg_flat_75_ffffff_40x100.png
ngpy/static/themes/base/images/ui-bg_glass_55_fbf9ee_1x400.png
ngpy/static/themes/base/images/ui-bg_glass_65_ffffff_1x400.png
ngpy/static/themes/base/images/ui-bg_glass_75_dadada_1x400.png
ngpy/static/themes/base/images/ui-bg_glass_75_e6e6e6_1x400.png
ngpy/static/themes/base/images/ui-bg_glass_95_fef1ec_1x400.png
ngpy/static/themes/base/images/ui-bg_highlight-soft_75_cccccc_1x100.png
ngpy/static/themes/base/images/ui-icons_222222_256x240.png
ngpy/static/themes/base/images/ui-icons_2e83ff_256x240.png
ngpy/static/themes/base/images/ui-icons_454545_256x240.png
ngpy/static/themes/base/images/ui-icons_888888_256x240.png
