Metadata-Version: 1.0
Name: ngpy
Version: 0.3
Summary: Web application for Monte Carlo simulation on nucleation and growth phenomena
Home-page: https://bitbucket.org/liuyxpp/ngpy
Author: Yi-Xin Liu
Author-email: liuyxpp@gmail.com
License: BSD
Platform: UNKNOWN
Classifier: Development Status :: 4 - Beta
Classifier: Environment :: Web Environment
Classifier: Intended Audience :: Science/Research
Classifier: Intended Audience :: Developers
Classifier: License :: OSI Approved :: BSD License
Classifier: Operating System :: POSIX :: Linux
Classifier: Programming Language :: Python
Classifier: Topic :: Internet :: WWW/HTTP :: Dynamic Content
Classifier: Topic :: Multimedia :: Graphics
Classifier: Topic :: Scientific/Engineering
Classifier: Topic :: Software Development :: Libraries :: Application Frameworks
